{
    "special_bonus_unique_underlord_3": "abyssal_underlord_atrophy_aura",
    "special_bonus_unique_beastmaster_2": "beastmaster_call_of_the_wild",
    "special_bonus_unique_beastmaster_3": "beastmaster_call_of_the_wild",
    "special_bonus_unique_bristleback": "bristleback_viscous_nasal_goo",
    "special_bonus_unique_bristleback_2": "bristleback_quill_spray",
    "special_bonus_unique_broodmother_3": "broodmother_spawn_spiderlings",
    //"special_bonus_unique_broodmother_4": "+20 Spiders Attack Damage",
    //"special_bonus_unique_broodmother_2": "+350 Spiders Health",
    //"special_bonus_unique_chen_4": "+1000 Creep Min Health",
    "special_bonus_unique_crystal_maiden_4": "crystal_maiden_brilliance_aura",
    "special_bonus_unique_dark_seer_4": "dark_seer_wall_of_replica",
    "special_bonus_unique_earthshaker_2": "earthshaker_echo_slam",
    "special_bonus_unique_ember_spirit_5": "ember_spirit_fire_remnant",
    //"special_bonus_unique_enigma_3": "+70 Eidolon Damage",
    "special_bonus_unique_faceless_void": "faceless_void_time_walk",
    //"special_bonus_unique_faceless_void_4": "+25% Backtrack",
    "special_bonus_unique_furion_2": "furion_force_of_nature",
    //"special_bonus_unique_furion": "2x Treant HP/Damage",
    "special_bonus_unique_invoker_1": "invoker_forge_spirit",
    //"special_bonus_unique_invoker_4": "Cataclysm",
    "special_bonus_unique_kunkka_3": "kunkka_ghostship",
    "special_bonus_unique_legion_commander_3": "legion_commander_moment_of_courage",
    //"special_bonus_unique_lich_2": "Attacks Apply 30% MS and AS Slow",
    //"special_bonus_unique_lone_druid_2": "+10 Spirit Bear Armor",
    //"special_bonus_unique_lone_druid_9": "0 Entangle Cooldown",
    "special_bonus_unique_lycan_3": "lycan_feral_impulse",
    "special_bonus_unique_lycan_2": "lycan_summon_wolves",
    //"special_bonus_unique_morphling_3": "+2 Multishot Adaptive Strike",
    "special_bonus_unique_nevermore_3": "nevermore_dark_lord",
    "special_bonus_unique_nevermore_1": "nevermore_necromastery",
    "special_bonus_unique_night_stalker_2": "night_stalker_hunter_in_the_night",
    "special_bonus_unique_pugna_4": "pugna_nether_blast",
    "special_bonus_unique_pugna_3": "pugna_nether_ward",
    "special_bonus_unique_queen_of_pain_2": "queenofpain_scream_of_pain",
    "special_bonus_unique_riki_2": "riki_smoke_screen",
    "special_bonus_unique_riki_1": "riki_permanent_invisibility",
    //"special_bonus_unique_shadow_shaman_1": "+1 Serpent Wards Max HP",
    //"special_bonus_unique_shadow_shaman_4": "+60 Wards Attack Damage",
    //"special_bonus_unique_silencer_2": "+2 Intelligence Steal",
    "special_bonus_unique_wraith_king_5": "skeleton_king_mortal_strike",
    //"special_bonus_unique_wraith_king_6": "+30 Skeletons Attack Damage",
    "special_bonus_unique_slardar_2": "slardar_bash",
    "special_bonus_unique_slardar": "slardar_bash",
    "special_bonus_unique_spirit_breaker_2": "spirit_breaker_charge_of_darkness",
    "special_bonus_unique_techies": "techies_suicide",
    //"special_bonus_unique_techies_4": "+25 Mines Movement Speed",
    "special_bonus_unique_tinker_3": "tinker_heat_seeking_missile",
    //"special_bonus_unique_treant_3": "3s Tree Respawn Time",
    //"special_bonus_unique_troll_warlord_3": "+50 Whirling Axes Damage",
    //"special_bonus_unique_troll_warlord": "-6s Whirling Axes Cooldown",
    "special_bonus_unique_tusk": "tusk_walrus_punch",
    //"special_bonus_unique_tusk_4": "12% Chance Walrus Punch",
    "special_bonus_unique_venomancer_5": "venomancer_venomous_gale",
    //"special_bonus_unique_visage_2": "+80 Familiars Movement Speed",
    "special_bonus_unique_visage_6": "visage_summon_familiars",
    //"special_bonus_unique_warlock_4": "Summons a Golem on death",
    "special_bonus_unique_weaver_3": "weaver_the_swarm",
    "special_bonus_unique_weaver_4": "weaver_the_swarm",
    "special_bonus_unique_witch_doctor_3": "witch_doctor_paralyzing_cask"
}